rp8000/__init__.py
rp8000/midi.py
Reloop_RP_8000_MIDI-1.1.dist-info/LICENSE
Reloop_RP_8000_MIDI-1.1.dist-info/METADATA
Reloop_RP_8000_MIDI-1.1.dist-info/WHEEL
Reloop_RP_8000_MIDI-1.1.dist-info/top_level.txt
Reloop_RP_8000_MIDI-1.1.dist-info/RECORD
