Metadata-Version: 2.1
Name: Reloop-RP-8000-MIDI
Version: 1.1
Summary: Reloop RP-8000 MIDI interface
Home-page: https://github.com/ChasonDeshotel/Reloop-RP-8000-MIDI
Author: Chason Deshotel
Author-email: me@chasondeshotel.com
Classifier: Programming Language :: Python :: 3
Classifier: License :: OSI Approved :: GNU General Public License v3 or later (GPLv3+)
Classifier: Operating System :: OS Independent
Requires-Python: >=3.7
License-File: LICENSE
